mopidy_qr/__init__.py
mopidy_qr/ext.conf
mopidy_qr/frontend.py
Mopidy_QR-0.0.1.dist-info/LICENSE
Mopidy_QR-0.0.1.dist-info/METADATA
Mopidy_QR-0.0.1.dist-info/WHEEL
Mopidy_QR-0.0.1.dist-info/entry_points.txt
Mopidy_QR-0.0.1.dist-info/top_level.txt
Mopidy_QR-0.0.1.dist-info/RECORD
